vudials_client/__init__.py
vudials_client/vudialsclient.py
vudials_client-2025.9.3.dist-info/METADATA
vudials_client-2025.9.3.dist-info/WHEEL
vudials_client-2025.9.3.dist-info/licenses/LICENSE
vudials_client-2025.9.3.dist-info/RECORD
