Metadata-Version: 2.4
Name: vudials_client
Version: 2025.9.3
Summary: A python client module for VU1 Dials from Streacom
Project-URL: Homepage, https://github.com/erinlkolp/vu1-dial-python-module
Project-URL: Issues, https://github.com/erinlkolp/vu1-dial-python-module/issues
Author-email: "Erin L. Kolp" <erinlkolpfoss@gmail.com>
License-Expression: MIT
License-File: LICENSE
Classifier: Operating System :: OS Independent
Classifier: Programming Language :: Python :: 3
Requires-Python: >=3.11
Requires-Dist: requests>=2.32.5
